odoo/addons/delivery_carrier_category/README.rst
odoo/addons/delivery_carrier_category/__init__.py
odoo/addons/delivery_carrier_category/__manifest__.py
odoo/addons/delivery_carrier_category/data/delivery_carrier_category.xml
odoo/addons/delivery_carrier_category/i18n/delivery_carrier_category.pot
odoo/addons/delivery_carrier_category/i18n/es.po
odoo/addons/delivery_carrier_category/i18n/it.po
odoo/addons/delivery_carrier_category/models/__init__.py
odoo/addons/delivery_carrier_category/models/delivery_carrier.py
odoo/addons/delivery_carrier_category/models/delivery_carrier_category.py
odoo/addons/delivery_carrier_category/readme/CONTRIBUTORS.rst
odoo/addons/delivery_carrier_category/readme/DESCRIPTION.rst
odoo/addons/delivery_carrier_category/readme/USAGE.rst
odoo/addons/delivery_carrier_category/security/delivery_carrier_category.xml
odoo/addons/delivery_carrier_category/static/description/icon.png
odoo/addons/delivery_carrier_category/static/description/index.html
odoo/addons/delivery_carrier_category/tests/__init__.py
odoo/addons/delivery_carrier_category/tests/test_carrier_category.py
odoo/addons/delivery_carrier_category/views/delivery_carrier.xml
odoo/addons/delivery_carrier_category/views/delivery_carrier_category.xml
odoo14_addon_delivery_carrier_category-14.0.1.0.1.dev10.dist-info/METADATA
odoo14_addon_delivery_carrier_category-14.0.1.0.1.dev10.dist-info/WHEEL
odoo14_addon_delivery_carrier_category-14.0.1.0.1.dev10.dist-info/top_level.txt
odoo14_addon_delivery_carrier_category-14.0.1.0.1.dev10.dist-info/RECORD
